ghdl/sqrt8.vhdl
-- https://www.csee.umbc.edu/portal/help/VHDL/samples/sqrt8.vhdl
-- sqrt8.vhdl  unsigned integer sqrt 8-bits computing unsigned integer 4-bits
--             sqrt(00000100) = 0010   sqrt(4)=2
--             sqrt(01000000) = 1000   sqrt(64)=8
library IEEE;
use IEEE.std_logic_1164.all;

entity Sm is  -- subtractor multiplexor 
  port ( x  : in  std_logic;
         y  : in  std_logic;
         b  : in  std_logic;
         u  : in  std_logic;
         d  : out std_logic;
         bo : out std_logic);
end Sm;

architecture circuits of Sm is
  signal t011, t111, t010, t001, t100, td : std_logic;
begin  -- circuits of Sm
  t011 <= (not x) and y and b;
  t111 <= x and y and b;
  t010 <= (not x) and y and (not b);
  t001 <= (not x) and (not y) and b;
  t100 <= x and (not y) and (not b);
  bo   <= t011 or t111 or t010 or t001;
  td   <= t100 or t001 or t010 or t111;
  d    <= td when u='1' else x;  
end architecture circuits;  -- of Sm

library IEEE;
use IEEE.std_logic_1164.all;

entity psqrt is
  port ( P : in  std_logic_vector(7 downto 0);
         U : out std_logic_vector(3 downto 0));
end psqrt;

architecture circuits of psqrt is
  signal zer : std_logic := '0';
  signal one : std_logic := '1';
  signal x00, x01, x02, x03, x04, x05, u_0 : std_logic;  
  signal b00, b01, b02, b03, b04, b05 : std_logic;  
  signal x12, x13, x14, x15, x16, u_1 : std_logic;  
  signal b12, b13, b14, b15, b16 : std_logic;  
  signal x24, x25, x26, x27, u_2 : std_logic;  
  signal b24, b25, b26, b27 : std_logic;  
  signal x36, x37, u_3 : std_logic;  
  signal b36, b37 : std_logic;  
begin  -- circuits of psqrt
  --                           x     y    b    u    d    bo
  s36: entity work.Sm port map(P(6), one, zer, u_3, x36, b36);
  s37: entity work.Sm port map(P(7), zer, b36, u_3, x37, b37);

  s24: entity work.Sm port map(P(4), one, zer, u_2, x24, b24);
  s25: entity work.Sm port map(P(5), zer, b24, u_2, x25, b25);
  s26: entity work.Sm port map(x36 , u_3, b25, u_2, x26, b26);
  s27: entity work.Sm port map(x37 , zer, b26, zer, x27, b27);

  s12: entity work.Sm port map(P(2), one, zer, u_1, x12, b12);
  s13: entity work.Sm port map(P(3), zer, b12, u_1, x13, b13);
  s14: entity work.Sm port map(x24 , u_2, b13, u_1, x14, b14);
  s15: entity work.Sm port map(x25 , u_3, b14, u_1, x15, b15);
  s16: entity work.Sm port map(x26 , zer, b15, zer, x16, b16);

  s00: entity work.Sm port map(P(0), one, zer, zer, x00, b00);
  s01: entity work.Sm port map(P(1), zer, b00, zer, x01, b01);
  s02: entity work.Sm port map(x12 , u_1, b01, zer, x02, b02);
  s03: entity work.Sm port map(x13 , u_2, b02, zer, x03, b03);
  s04: entity work.Sm port map(x14 , u_3, b03, zer, x04, b04);
  s05: entity work.Sm port map(x15 , zer, b04, zer, x05, b05);
  u_0  <= not b05;
  u_1  <= not b16;
  u_2  <= not b27;
  u_3  <= not b37;
  U(0) <= u_0;
  U(1) <= u_1;
  U(2) <= u_2;
  U(3) <= u_3;
end architecture circuits;  -- of psqrt

library STD;
use STD.textio.all;
library IEEE;
use IEEE.std_logic_1164.all;
use IEEE.std_logic_textio.all;
use IEEE.numeric_std.all;

entity sqrt8 is  -- test driver
end sqrt8;

architecture test of sqrt8 is
  signal P : std_logic_vector(7 downto 0);
  signal U : std_logic_vector(3 downto 0);

  procedure print(P : std_logic_vector(7 downto 0);
                  U : std_logic_vector(3 downto 0)) is
    variable my_line : line;
    alias swrite is write [line, string, side, width] ;
  begin
    swrite(my_line, "sqrt( ");
    write(my_line, P);
    swrite(my_line, " )= ");
    write(my_line, U);
    writeline(output, my_line);
  end print;
  
begin  -- test of sqrt8
  s1: entity work.psqrt  port map(P, U);    -- parallel code
  driver: process                      -- serial code
          begin  -- process driver
            for I in 0 to 255 loop
              P <= std_logic_vector(to_unsigned(I,8));
              wait for 2 ns;
              print(P, U);
            end loop;
          end process driver;
end architecture test;   -- of sqrt8

ghdl/sqrt8.vcd
$date
  Thu Oct  7 07:25:22 2021
$end
$version
  GHDL v0
$end
$timescale
  1 fs
$end
$scope module standard $end
$upscope $end
$scope module textio $end
$upscope $end
$scope module std_logic_1164 $end
$upscope $end
$scope module std_logic_textio $end
$upscope $end
$scope module numeric_std $end
$upscope $end
$scope module sqrt8 $end
$var reg 8 ! p[7:0] $end
$var reg 4 " u[3:0] $end
$scope module s1 $end
$var reg 8 # p[7:0] $end
$var reg 4 $ u[3:0] $end
$var reg 1 % zer $end
$var reg 1 & one $end
$var reg 1 ' x00 $end
$var reg 1 ( x01 $end
$var reg 1 ) x02 $end
$var reg 1 * x03 $end
$var reg 1 + x04 $end
$var reg 1 , x05 $end
$var reg 1 - u_0 $end
$var reg 1 . b00 $end
$var reg 1 / b01 $end
$var reg 1 0 b02 $end
$var reg 1 1 b03 $end
$var reg 1 2 b04 $end
$var reg 1 3 b05 $end
$var reg 1 4 x12 $end
$var reg 1 5 x13 $end
$var reg 1 6 x14 $end
$var reg 1 7 x15 $end
$var reg 1 8 x16 $end
$var reg 1 9 u_1 $end
$var reg 1 : b12 $end
$var reg 1 ; b13 $end
$var reg 1 < b14 $end
$var reg 1 = b15 $end
$var reg 1 > b16 $end
$var reg 1 ? x24 $end
$var reg 1 @ x25 $end
$var reg 1 A x26 $end
$var reg 1 B x27 $end
$var reg 1 C u_2 $end
$var reg 1 D b24 $end
$var reg 1 E b25 $end
$var reg 1 F b26 $end
$var reg 1 G b27 $end
$var reg 1 H x36 $end
$var reg 1 I x37 $end
$var reg 1 J u_3 $end
$var reg 1 K b36 $end
$var reg 1 L b37 $end
$scope module s36 $end
$var reg 1 M x $end
$var reg 1 N y $end
$var reg 1 O b $end
$var reg 1 P u $end
$var reg 1 Q d $end
$var reg 1 R bo $end
$var reg 1 S t011 $end
$var reg 1 T t111 $end
$var reg 1 U t010 $end
$var reg 1 V t001 $end
$var reg 1 W t100 $end
$var reg 1 X td $end
$upscope $end
$scope module s37 $end
$var reg 1 Y x $end
$var reg 1 Z y $end
$var reg 1 [ b $end
$var reg 1 \ u $end
$var reg 1 ] d $end
$var reg 1 ^ bo $end
$var reg 1 _ t011 $end
$var reg 1 ` t111 $end
$var reg 1 a t010 $end
$var reg 1 b t001 $end
$var reg 1 c t100 $end
$var reg 1 d td $end
$upscope $end
$scope module s24 $end
$var reg 1 e x $end
$var reg 1 f y $end
$var reg 1 g b $end
$var reg 1 h u $end
$var reg 1 i d $end
$var reg 1 j bo $end
$var reg 1 k t011 $end
$var reg 1 l t111 $end
$var reg 1 m t010 $end
$var reg 1 n t001 $end
$var reg 1 o t100 $end
$var reg 1 p td $end
$upscope $end
$scope module s25 $end
$var reg 1 q x $end
$var reg 1 r y $end
$var reg 1 s b $end
$var reg 1 t u $end
$var reg 1 u d $end
$var reg 1 v bo $end
$var reg 1 w t011 $end
$var reg 1 x t111 $end
$var reg 1 y t010 $end
$var reg 1 z t001 $end
$var reg 1 { t100 $end
$var reg 1 | td $end
$upscope $end
$scope module s26 $end
$var reg 1 } x $end
$var reg 1 !" y $end
$var reg 1 "" b $end
$var reg 1 #" u $end
$var reg 1 $" d $end
$var reg 1 %" bo $end
$var reg 1 &" t011 $end
$var reg 1 '" t111 $end
$var reg 1 (" t010 $end
$var reg 1 )" t001 $end
$var reg 1 *" t100 $end
$var reg 1 +" td $end
$upscope $end
$scope module s27 $end
$var reg 1 ," x $end
$var reg 1 -" y $end
$var reg 1 ." b $end
$var reg 1 /" u $end
$var reg 1 0" d $end
$var reg 1 1" bo $end
$var reg 1 2" t011 $end
$var reg 1 3" t111 $end
$var reg 1 4" t010 $end
$var reg 1 5" t001 $end
$var reg 1 6" t100 $end
$var reg 1 7" td $end
$upscope $end
$scope module s12 $end
$var reg 1 8" x $end
$var reg 1 9" y $end
$var reg 1 :" b $end
$var reg 1 ;" u $end
$var reg 1 <" d $end
$var reg 1 =" bo $end
$var reg 1 >" t011 $end
$var reg 1 ?" t111 $end
$var reg 1 @" t010 $end
$var reg 1 A" t001 $end
$var reg 1 B" t100 $end
$var reg 1 C" td $end
$upscope $end
$scope module s13 $end
$var reg 1 D" x $end
$var reg 1 E" y $end
$var reg 1 F" b $end
$var reg 1 G" u $end
$var reg 1 H" d $end
$var reg 1 I" bo $end
$var reg 1 J" t011 $end
$var reg 1 K" t111 $end
$var reg 1 L" t010 $end
$var reg 1 M" t001 $end
$var reg 1 N" t100 $end
$var reg 1 O" td $end
$upscope $end
$scope module s14 $end
$var reg 1 P" x $end
$var reg 1 Q" y $end
$var reg 1 R" b $end
$var reg 1 S" u $end
$var reg 1 T" d $end
$var reg 1 U" bo $end
$var reg 1 V" t011 $end
$var reg 1 W" t111 $end
$var reg 1 X" t010 $end
$var reg 1 Y" t001 $end
$var reg 1 Z" t100 $end
$var reg 1 [" td $end
$upscope $end
$scope module s15 $end
$var reg 1 \" x $end
$var reg 1 ]" y $end
$var reg 1 ^" b $end
$var reg 1 _" u $end
$var reg 1 `" d $end
$var reg 1 a" bo $end
$var reg 1 b" t011 $end
$var reg 1 c" t111 $end
$var reg 1 d" t010 $end
$var reg 1 e" t001 $end
$var reg 1 f" t100 $end
$var reg 1 g" td $end
$upscope $end
$scope module s16 $end
$var reg 1 h" x $end
$var reg 1 i" y $end
$var reg 1 j" b $end
$var reg 1 k" u $end
$var reg 1 l" d $end
$var reg 1 m" bo $end
$var reg 1 n" t011 $end
$var reg 1 o" t111 $end
$var reg 1 p" t010 $end
$var reg 1 q" t001 $end
$var reg 1 r" t100 $end
$var reg 1 s" td $end
$upscope $end
$scope module s00 $end
$var reg 1 t" x $end
$var reg 1 u" y $end
$var reg 1 v" b $end
$var reg 1 w" u $end
$var reg 1 x" d $end
$var reg 1 y" bo $end
$var reg 1 z" t011 $end
$var reg 1 {" t111 $end
$var reg 1 |" t010 $end
$var reg 1 }" t001 $end
$var reg 1 !# t100 $end
$var reg 1 "# td $end
$upscope $end
$scope module s01 $end
$var reg 1 ## x $end
$var reg 1 $# y $end
$var reg 1 %# b $end
$var reg 1 &# u $end
$var reg 1 '# d $end
$var reg 1 (# bo $end
$var reg 1 )# t011 $end
$var reg 1 *# t111 $end
$var reg 1 +# t010 $end
$var reg 1 ,# t001 $end
$var reg 1 -# t100 $end
$var reg 1 .# td $end
$upscope $end
$scope module s02 $end
$var reg 1 /# x $end
$var reg 1 0# y $end
$var reg 1 1# b $end
$var reg 1 2# u $end
$var reg 1 3# d $end
$var reg 1 4# bo $end
$var reg 1 5# t011 $end
$var reg 1 6# t111 $end
$var reg 1 7# t010 $end
$var reg 1 8# t001 $end
$var reg 1 9# t100 $end
$var reg 1 :# td $end
$upscope $end
$scope module s03 $end
$var reg 1 ;# x $end
$var reg 1 <# y $end
$var reg 1 =# b $end
$var reg 1 ># u $end
$var reg 1 ?# d $end
$var reg 1 @# bo $end
$var reg 1 A# t011 $end
$var reg 1 B# t111 $end
$var reg 1 C# t010 $end
$var reg 1 D# t001 $end
$var reg 1 E# t100 $end
$var reg 1 F# td $end
$upscope $end
$scope module s04 $end
$var reg 1 G# x $end
$var reg 1 H# y $end
$var reg 1 I# b $end
$var reg 1 J# u $end
$var reg 1 K# d $end
$var reg 1 L# bo $end
$var reg 1 M# t011 $end
$var reg 1 N# t111 $end
$var reg 1 O# t010 $end
$var reg 1 P# t001 $end
$var reg 1 Q# t100 $end
$var reg 1 R# td $end
$upscope $end
$scope module s05 $end
$var reg 1 S# x $end
$var reg 1 T# y $end
$var reg 1 U# b $end
$var reg 1 V# u $end
$var reg 1 W# d $end
$var reg 1 X# bo $end
$var reg 1 Y# t011 $end
$var reg 1 Z# t111 $end
$var reg 1 [# t010 $end
$var reg 1 \# t001 $end
$var reg 1 ]# t100 $end
$var reg 1 ^# td $end
$upscope $end
$upscope $end
$upscope $end
$enddefinitions $end
#0
b00000000 !
b0000 "
b00000000 #
b0000 $
0%
1&
0'
0(
0)
0*
0+
0,
0-
1.
1/
10
11
12
13
04
05
06
07
08
09
1:
1;
1<
1=
1>
0?
0@
0A
0B
0C
1D
1E
1F
1G
0H
0I
0J
1K
1L
0M
1N
0O
0P
0Q
1R
0S
0T
1U
0V
0W
1X
0Y
0Z
1[
0\
0]
1^
0_
0`
0a
1b
0c
1d
0e
1f
0g
0h
0i
1j
0k
0l
1m
0n
0o
1p
0q
0r
1s
0t
0u
1v
0w
0x
0y
1z
0{
1|
0}
0!"
1""
0#"
0$"
1%"
0&"
0'"
0("
1)"
0*"
1+"
0,"
0-"
1."
0/"
00"
11"
02"
03"
04"
15"
06"
17"
08"
19"
0:"
0;"
0<"
1="
0>"
0?"
1@"
0A"
0B"
1C"
0D"
0E"
1F"
0G"
0H"
1I"
0J"
0K"
0L"
1M"
0N"
1O"
0P"
0Q"
1R"
0S"
0T"
1U"
0V"
0W"
0X"
1Y"
0Z"
1["
0\"
0]"
1^"
0_"
0`"
1a"
0b"
0c"
0d"
1e"
0f"
1g"
0h"
0i"
1j"
0k"
0l"
1m"
0n"
0o"
0p"
1q"
0r"
1s"
0t"
1u"
0v"
0w"
0x"
1y"
0z"
0{"
1|"
0}"
0!#
1"#
0##
0$#
1%#
0&#
0'#
1(#
0)#
0*#
0+#
1,#
0-#
1.#
0/#
00#
11#
02#
03#
14#
05#
06#
07#
18#
09#
1:#
0;#
0<#
1=#
0>#
0?#
1@#
0A#
0B#
0C#
1D#
0E#
1F#
0G#
0H#
1I#
0J#
0K#
1L#
0M#
0N#
0O#
1P#
0Q#
1R#
0S#
0T#
1U#
0V#
0W#
1X#
0Y#
0Z#
0[#
1\#
0]#
1^#
#2000000
b00000001 !
b0001 "
b00000001 #
b0001 $
1'
1-
0.
0/
00
01
02
03
1t"
1x"
0y"
0|"
0"#
0%#
0(#
0,#
0.#
01#
04#
08#
0:#
0=#
0@#
0D#
0F#
0I#
0L#
0P#
0R#
0U#
0X#
0\#
0^#
#4000000
b00000010 !
b00000010 #
0'
1(
1.
0t"
0x"
1y"
1|"
1"#
1##
1%#
1'#
0-#
0.#
#6000000
b00000011 !
b00000011 #
1'
0.
1t"
1x"
0y"
0|"
0"#
0%#
1-#
1.#
#8000000
b00000100 !
b0010 "
b00000100 #
b0010 $
0'
0(
0)
0-
1.
1/
10
11
12
13
04
19
0:
0;
0<
0=
0>
18"
1;"
0<"
0="
0@"
0C"
0F"
1G"
0I"
0M"
0O"
0R"
1S"
0U"
0Y"
0["
0^"
1_"
0a"
0e"
0g"
0j"
0m"
0q"
0s"
0t"
0x"
1y"
1|"
1"#
0##
1%#
0'#
1(#
1,#
0-#
1.#
0/#
10#
11#
03#
14#
15#
06#
09#
0:#
1=#
1@#
1D#
1F#
1I#
1L#
1P#
1R#
1U#
1X#
1\#
1^#
#10000000
b00000101 !
b00000101 #
1'
0.
0/
1t"
1x"
0y"
0|"
0"#
0%#
0(#
0,#
0.#
01#
05#
17#
1:#
#12000000
b00000110 !
b00000110 #
0'
1(
1.
0t"
0x"
1y"
1|"
1"#
1##
1%#
1'#
0-#
0.#
#14000000
b00000111 !
b00000111 #
1'
0.
1t"
1x"
0y"
0|"
0"#
0%#
1-#
1.#
#16000000
b00001000 !
b0010 "
b00001000 #
b0010 $
0'
0(
1)
0*
0-
1.
1/
10
11
12
13
14
05
1:
08"
1<"
1="
1@"
1C"
1D"
1F"
0H"
0N"
0O"
0t"
0x"
1y"
1|"
1"#
0##
1%#
0'#
1(#
1,#
0-#
1.#
1/#
11#
13#
14#
16#
07#
1:#
0;#
1=#
0?#
1@#
1D#
1F#
1I#
1L#
1P#
1R#
1U#
1X#
1\#
1^#
#18000000
b00001001 !
b0011 "
b00001001 #
b0011 $
1'
1-
0.
0/
00
01
02
03
1t"
1x"
0y"
0|"
0"#
0%#
0(#
0,#
0.#
01#
04#
06#
0:#
0=#
0@#
0D#
0F#
0I#
0L#
0P#
0R#
0U#
0X#
0\#
0^#
#20000000
b00001010 !
b00001010 #
0'
1(
1.
0t"
0x"
1y"
1|"
1"#
1##
1%#
1'#
0-#
0.#
#22000000
b00001011 !
b00001011 #
1'
0.
1t"
1x"
0y"
0|"
0"#
0%#
1-#
1.#
#24000000
b00001100 !
b00001100 #
0'
0(
0)
1*
1.
1/
10
04
15
0:
18"
0<"
0="
0@"
0C"
0F"
1H"
1N"
1O"
0t"
0x"
1y"
1|"
1"#
0##
1%#
0'#
1(#
1,#
0-#
1.#
0/#
11#
03#
14#
15#
07#
0:#
1;#
1=#
1?#
#26000000
b00001101 !
b00001101 #
1'
0.
0/
1t"
1x"
0y"
0|"
0"#
0%#
0(#
0,#
0.#
01#
05#
17#
1:#
#28000000
b00001110 !
b00001110 #
0'
1(
1.
0t"
0x"
1y"
1|"
1"#
1##
1%#
1'#
0-#
0.#
#30000000
b00001111 !
b00001111 #
1'
0.
1t"
1x"
0y"
0|"
0"#
0%#
1-#
1.#
#32000000
b00010000 !
b0100 "
b00010000 #
b0100 $
0'
0(
0)
0*
0+
0,
0-
1.
1/
10
11
12
13
04
05
06
07
09
1:
1;
1<
1=
1>
0?
1C
0D
0E
0F
0G
1e
1h
0i
0j
0m
0p
0s
1t
0v
0z
0|
0""
1#"
0%"
0)"
0+"
0."
01"
05"
07"
08"
0;"
0<"
1="
1@"
1C"
0D"
1F"
0G"
0H"
1I"
1M"
0N"
1O"
0P"
1Q"
1R"
0S"
0T"
1U"
1V"
0W"
0Z"
0["
1^"
0_"
0`"
1a"
1e"
1g"
1j"
1m"
1q"
1s"
0t"
0x"
1y"
1|"
1"#
0##
1%#
0'#
1(#
1,#
0-#
1.#
0/#
00#
11#
03#
14#
06#
07#
18#
1:#
0;#
1<#
1=#
0?#
1@#
1A#
0B#
0C#
0D#
0E#
0F#
0G#
1I#
0K#
1L#
1P#
0Q#
1R#
0S#
1U#
0W#
1X#
1\#
0]#
1^#
#34000000
b00010001 !
b00010001 #
1'
0.
0/
00
1t"
1x"
0y"
0|"
0"#
0%#
0(#
0,#
0.#
01#
04#
08#
0:#
0=#
0A#
1C#
1F#
#36000000
b00010010 !
b00010010 #
0'
1(
1.
0t"
0x"
1y"
1|"
1"#
1##
1%#
1'#
0-#
0.#
#38000000
b00010011 !
b00010011 #
1'
0.
1t"
1x"
0y"
0|"
0"#
0%#
1-#
1.#
#40000000
b00010100 !
b00010100 #
0'
0(
1)
1.
1/
14
0:
0;
18"
1<"
0="
0@"
0C"
0F"
0I"
0M"
0O"
0R"
0V"
1X"
1["
0t"
0x"
1y"
1|"
1"#
0##
1%#
0'#
1(#
1,#
0-#
1.#
1/#
11#
13#
09#
0:#
#42000000
b00010101 !
b00010101 #
1'
0.
0/
1t"
1x"
0y"
0|"
0"#
0%#
0(#
0,#
0.#
01#
19#
1:#
#44000000
b00010110 !
b00010110 #
0'
1(
1.
0t"
0x"
1y"
1|"
1"#
1##
1%#
1'#
0-#
0.#
#46000000
b00010111 !
b00010111 #
1'
0.
1t"
1x"
0y"
0|"
0"#
0%#
1-#
1.#
#48000000
b00011000 !
b0100 "
b00011000 #
b0100 $
0'
0(
0)
1*
0-
1.
1/
10
11
12
13
04
15
1:
08"
0<"
1="
1@"
1C"
1D"
1F"
1H"
0N"
0O"
0t"
0x"
1y"
1|"
1"#
0##
1%#
0'#
1(#
1,#
0-#
1.#
0/#
11#
03#
14#
18#
09#
1:#
1;#
1=#
1?#
1@#
1B#
0C#
1F#
1I#
1L#
1P#
1R#
1U#
1X#
1\#
1^#
#50000000
b00011001 !
b0101 "
b00011001 #
b0101 $
1'
1-
0.
0/
00
01
02
03
1t"
1x"
0y"
0|"
0"#
0%#
0(#
0,#
0.#
01#
04#
08#
0:#
0=#
0@#
0B#
0F#
0I#
0L#
0P#
0R#
0U#
0X#
0\#
0^#
#52000000
b00011010 !
b00011010 #
0'
1(
1.
0t"
0x"
1y"
1|"
1"#
1##
1%#
1'#
0-#
0.#
#54000000
b00011011 !
b00011011 #
1'
0.
1t"
1x"
0y"
0|"
0"#
0%#
1-#
1.#
#56000000
b00011100 !
b00011100 #
0'
0(
1)
1.
1/
14
0:
18"
1<"
0="
0@"
0C"
0F"
1N"
1O"
0t"
0x"
1y"
1|"
1"#
0##
1%#
0'#
1(#
1,#
0-#
1.#
1/#
11#
13#
09#
0:#
#58000000
b00011101 !
b00011101 #
1'
0.
0/
1t"
1x"
0y"
0|"
0"#
0%#
0(#
0,#
0.#
01#
19#
1:#
#60000000
b00011110 !
b00011110 #
0'
1(
1.
0t"
0x"
1y"
1|"
1"#
1##
1%#
1'#
0-#
0.#
#62000000
b00011111 !
b00011111 #
1'
0.
1t"
1x"
0y"
0|"
0"#
0%#
1-#
1.#
#64000000
b00100000 !
b0101 "
b00100000 #
b0101 $
0'
0(
0)
0*
1+
0,
1.
1/
10
11
02
04
05
16
07
09
1:
1;
1<
1=
1>
1?
0@
1D
0e
1i
1j
1m
1p
1q
1s
0u
0{
0|
08"
0;"
0<"
1="
1@"
1C"
0D"
1F"
0G"
0H"
1I"
1M"
0N"
1O"
1P"
1R"
0S"
1T"
1U"
1W"
0X"
1["
0\"
1^"
0_"
0`"
1a"
1e"
1g"
1j"
1m"
1q"
1s"
0t"
0x"
1y"
1|"
1"#
0##
1%#
0'#
1(#
1,#
0-#
1.#
0/#
00#
11#
03#
14#
05#
06#
18#
09#
1:#
0;#
1=#
0?#
1@#
1A#
0B#
0C#
0F#
1G#
1I#
1K#
0L#
0P#
0R#
0S#
0U#
0W#
0]#
0^#
#66000000
b00100001 !
b00100001 #
1'
0.
0/
00
1t"
1x"
0y"
0|"
0"#
0%#
0(#
0,#
0.#
01#
04#
08#
0:#
0=#
0A#
1C#
1F#
#68000000
b00100010 !
b00100010 #
0'
1(
1.
0t"
0x"
1y"
1|"
1"#
1##
1%#
1'#
0-#
0.#
#70000000
b00100011 !
b00100011 #
1'
0.
1t"
1x"
0y"
0|"
0"#
0%#
1-#
1.#
#72000000
b00100100 !
b0110 "
b00100100 #
b0110 $
0'
0(
0)
0+
0-
1.
1/
10
12
13
04
06
19
0:
0;
0<
0=
0>
18"
1;"
0<"
0="
0@"
0C"
0F"
1G"
0I"
0M"
0O"
0R"
1S"
0T"
0U"
0W"
0["
0^"
1_"
0a"
0e"
0g"
0j"
0m"
0q"
0s"
0t"
0x"
1y"
1|"
1"#
0##
1%#
0'#
1(#
1,#
0-#
1.#
0/#
10#
11#
03#
14#
15#
06#
09#
0:#
1=#
1A#
0C#
0F#
0G#
0K#
1L#
1P#
1R#
1U#
1X#
1\#
1^#
#74000000
b00100101 !
b00100101 #
1'
0.
0/
1t"
1x"
0y"
0|"
0"#
0%#
0(#
0,#
0.#
01#
05#
17#
1:#
#76000000
b00100110 !
b00100110 #
0'
1(
1.
0t"
0x"
1y"
1|"
1"#
1##
1%#
1'#
0-#
0.#
#78000000
b00100111 !
b00100111 #
1'
0.
1t"
1x"
0y"
0|"
0"#
0%#
1-#
1.#
#80000000
b00101000 !
b00101000 #
0'
0(
1)
0*
1.
1/
10
14
05
1:
08"
1<"
1="
1@"
1C"
1D"
1F"
0H"
0N"
0O"
0t"
0x"
1y"
1|"
1"#
0##
1%#
0'#
1(#
1,#
0-#
1.#
1/#
11#
13#
14#
16#
07#
1:#
0;#
1=#
0?#
1A#
0B#
0C#
0F#
#82000000
b00101001 !
b00101001 #
1'
0.
0/
00
1t"
1x"
0y"
0|"
0"#
0%#
0(#
0,#
0.#
01#
04#
06#
0:#
0=#
0A#
1C#
1F#
#84000000
b00101010 !
b00101010 #
0'
1(
1.
0t"
0x"
1y"
1|"
1"#
1##
1%#
1'#
0-#
0.#
#86000000
b00101011 !
b00101011 #
1'
0.
1t"
1x"
0y"
0|"
0"#
0%#
1-#
1.#
#88000000
b00101100 !
b00101100 #
0'
0(
0)
1*
1.
1/
10
04
15
0:
18"
0<"
0="
0@"
0C"
0F"
1H"
1N"
1O"
0t"
0x"
1y"
1|"
1"#
0##
1%#
0'#
1(#
1,#
0-#
1.#
0/#
11#
03#
14#
15#
07#
0:#
1;#
1=#
1?#
1B#
0C#
#90000000
b00101101 !
b00101101 #
1'
0.
0/
1t"
1x"
0y"
0|"
0"#
0%#
0(#
0,#
0.#
01#
05#
17#
1:#
#92000000
b00101110 !
b00101110 #
0'
1(
1.
0t"
0x"
1y"
1|"
1"#
1##
1%#
1'#
0-#
0.#
#94000000
b00101111 !
b00101111 #
1'
0.
1t"
1x"
0y"
0|"
0"#
0%#
1-#
1.#
#96000000
b00110000 !
b0110 "
b00110000 #
b0110 $
0'
0(
1)
1*
0+
0-
1.
1/
10
11
12
13
14
15
06
1:
1;
1<
0?
1@
0D
1e
0i
0j
0m
0p
0s
1u
1{
1|
08"
1<"
1="
1@"
1C"
0D"
1F"
1H"
1I"
1M"
0N"
1O"
0P"
1R"
0T"
1U"
1V"
0X"
0["
1\"
1^"
0t"
0x"
1y"
1|"
1"#
0##
1%#
0'#
1(#
1,#
0-#
1.#
1/#
11#
13#
14#
16#
07#
1:#
1;#
1=#
1?#
1@#
0A#
1B#
1F#
0G#
1I#
0K#
1L#
1P#
1R#
1U#
1X#
1\#
1^#
#98000000
b00110001 !
b0111 "
b00110001 #
b0111 $
1'
1-
0.
0/
00
01
02
03
1t"
1x"
0y"
0|"
0"#
0%#
0(#
0,#
0.#
01#
04#
06#
0:#
0=#
0@#
0B#
0F#
0I#
0L#
0P#
0R#
0U#
0X#
0\#
0^#
#100000000
b00110010 !
b00110010 #
0'
1(
1.
0t"
0x"
1y"
1|"
1"#
1##
1%#
1'#
0-#
0.#
#102000000
b00110011 !
b00110011 #
1'
0.
1t"
1x"
0y"
0|"
0"#
0%#
1-#
1.#
#104000000
b00110100 !
b00110100 #
0'
0(
0)
0*
1+
1.
1/
10
11
04
05
16
0:
0;
18"
0<"
0="
0@"
0C"
0F"
0H"
0I"
0M"
0O"
0R"
1T"
0V"
1X"
1["
0t"
0x"
1y"
1|"
1"#
0##
1%#
0'#
1(#
1,#
0-#
1.#
0/#
11#
03#
14#
15#
07#
0:#
0;#
1=#
0?#
1@#
1A#
1G#
1I#
1K#
#106000000
b00110101 !
b00110101 #
1'
0.
0/
1t"
1x"
0y"
0|"
0"#
0%#
0(#
0,#
0.#
01#
05#
17#
1:#
#108000000
b00110110 !
b00110110 #
0'
1(
1.
0t"
0x"
1y"
1|"
1"#
1##
1%#
1'#
0-#
0.#
#110000000
b00110111 !
b00110111 #
1'
0.
1t"
1x"
0y"
0|"
0"#
0%#
1-#
1.#
#112000000
b00111000 !
b00111000 #
0'
0(
1)
0*
1.
1/
10
14
05
1:
08"
1<"
1="
1@"
1C"
1D"
1F"
0H"
0N"
0O"
0t"
0x"
1y"
1|"
1"#
0##
1%#
0'#
1(#
1,#
0-#
1.#
1/#
11#
13#
14#
16#
07#
1:#
0;#
1=#
0?#
1A#
0B#
0C#
0F#
#114000000
b00111001 !
b00111001 #
1'
0.
0/
00
1t"
1x"
0y"
0|"
0"#
0%#
0(#
0,#
0.#
01#
04#
06#
0:#
0=#
0A#
1C#
1F#
#116000000
b00111010 !
b00111010 #
0'
1(
1.
0t"
0x"
1y"
1|"
1"#
1##
1%#
1'#
0-#
0.#
#118000000
b00111011 !
b00111011 #
1'
0.
1t"
1x"
0y"
0|"
0"#
0%#
1-#
1.#
#120000000
b00111100 !
b00111100 #
0'
0(
0)
1*
1.
1/
10
04
15
0:
18"
0<"
0="
0@"
0C"
0F"
1H"
1N"
1O"
0t"
0x"
1y"
1|"
1"#
0##
1%#
0'#
1(#
1,#
0-#
1.#
0/#
11#
03#
14#
15#
07#
0:#
1;#
1=#
1?#
1B#
0C#
#122000000
b00111101 !
b00111101 #
1'
0.
0/
1t"
1x"
0y"
0|"
0"#
0%#
0(#
0,#
0.#
01#
05#
17#
1:#
#124000000
b00111110 !
b00111110 #
0'
1(
1.
0t"
0x"
1y"
1|"
1"#
1##
1%#
1'#
0-#
0.#
#126000000
b00111111 !
b00111111 #
1'
0.
1t"
1x"
0y"
0|"
0"#
0%#
1-#
1.#
#128000000
b01000000 !
b1000 "
b01000000 #
b1000 $
0'
0(
0)
0*
0+
0,
0-
1.
1/
10
11
12
13
04
05
06
07
08
09
1:
1;
1<
1=
1>
0?
0@
0A
0C
1D
1E
1F
1G
0H
1J
0K
0L
1M
1P
0Q
0R
0U
0X
0[
1\
0^
0b
0d
0e
0h
0i
1j
1m
1p
0q
1s
0t
0u
1v
1z
0{
1|
0}
1!"
1""
0#"
0$"
1%"
1&"
0'"
0*"
0+"
1."
11"
15"
17"
08"
0;"
0<"
1="
1@"
1C"
0D"
1F"
0G"
0H"
1I"
1M"
0N"
1O"
0P"
0Q"
1R"
0S"
0T"
1U"
0W"
0X"
1Y"
1["
0\"
1]"
1^"
0_"
0`"
1a"
1b"
0c"
0d"
0e"
0g"
0h"
1j"
0l"
1m"
1q"
0r"
1s"
0t"
0x"
1y"
1|"
1"#
0##
1%#
0'#
1(#
1,#
0-#
1.#
0/#
00#
11#
03#
14#
06#
07#
18#
1:#
0;#
0<#
1=#
0?#
1@#
0A#
0B#
1D#
1F#
0G#
1H#
1I#
0K#
1L#
1M#
0N#
0O#
0R#
0S#
1U#
0W#
1X#
1\#
0]#
1^#
#130000000
b01000001 !
b01000001 #
1'
0.
0/
00
01
1t"
1x"
0y"
0|"
0"#
0%#
0(#
0,#
0.#
01#
04#
08#
0:#
0=#
0@#
0D#
0F#
0I#
0M#
1O#
1R#
#132000000
b01000010 !
b01000010 #
0'
1(
1.
0t"
0x"
1y"
1|"
1"#
1##
1%#
1'#
0-#
0.#
#134000000
b01000011 !
b01000011 #
1'
0.
1t"
1x"
0y"
0|"
0"#
0%#
1-#
1.#
