ghdl/sr_ff.vhdl
-- https://technobyte.org/vhdl-code-flip-flops-behavioral/
library IEEE;
use IEEE.STD_LOGIC_1164.ALL;
use IEEE.STD_LOGIC_ARITH.ALL;
use IEEE.STD_LOGIC_UNSIGNED.ALL;
entity SR_FLIPFLOP_SOURCE is
    Port ( S,R,RST,CLK : in  STD_LOGIC;
           Q,Qb : out STD_LOGIC);
end SR_FLIPFLOP_SOURCE;

architecture Behavioral of SR_FLIPFLOP_SOURCE is

begin

process (S,R,RST,CLK)

begin

if (RST = '1') then
Q <= '0';
elsif (RISING_EDGE(CLK))then
if (S /= R) then
Q <= S;
Qb <= R;
elsif (S = '1' AND R = '1') then
Q <= 'Z';
Qb <= 'Z';

end if;
end if; 
end process;
end Behavioral;

ghdl/sr_ff_tb.vhdl
library IEEE;
use IEEE.STD_LOGIC_1164.ALL;
use IEEE.STD_LOGIC_ARITH.ALL;
use IEEE.STD_LOGIC_UNSIGNED.ALL;

entity SR_FF_tb is
end entity;

architecture tb of SR_FF_tb is

component SR_FLIPFLOP_SOURCE is
Port ( S,R,RST,CLK : in STD_LOGIC;
Q,Qb : out STD_LOGIC);
end component;

signal S, R, RST, CLK, Q, Qb : STD_LOGIC;

begin
uut: SR_FLIPFLOP_SOURCE port map(
S => S,
R => R,
RST => RST,
CLK => CLK,
Q => Q,
Qb => Qb);

Clock : process
begin

CLK <= '0';
wait for 10 ns;
CLK <= '1';
wait for 10 ns;

end process;

Stim : process
begin

RST <= '0';

S <= '0';
R <= '0';
wait for 20 ns;

S <= '0';
R <= '1';
wait for 20 ns;

S <= '1';
R <= '0';
wait for 20 ns;

S <= '1';
R <= '1';
wait for 20 ns;

end process;
end tb;

ghdl/sr_ff.vcd
$date
  Tue Oct 12 06:14:59 2021
$end
$version
  GHDL v0
$end
$timescale
  1 fs
$end
$scope module standard $end
$upscope $end
$scope module std_logic_1164 $end
$upscope $end
$scope module std_logic_arith $end
$upscope $end
$scope module std_logic_unsigned $end
$upscope $end
$scope module sr_ff_tb $end
$var reg 1 ! s $end
$var reg 1 " r $end
$var reg 1 # rst $end
$var reg 1 $ clk $end
$var reg 1 % q $end
$var reg 1 & qb $end
$scope module uut $end
$var reg 1 ' s $end
$var reg 1 ( r $end
$var reg 1 ) rst $end
$var reg 1 * clk $end
$var reg 1 + q $end
$var reg 1 , qb $end
$upscope $end
$upscope $end
$enddefinitions $end
#0
0!
0"
0#
0$
U%
U&
0'
0(
0)
0*
U+
U,
#10000000
1$
1*
#20000000
1"
0$
1(
0*
#30000000
1$
0%
1&
1*
0+
1,
#40000000
1!
0"
0$
1'
0(
0*
#50000000
1$
1%
0&
1*
1+
0,
#60000000
1"
0$
1(
0*
#70000000
1$
Z%
Z&
1*
Z+
Z,
#80000000
0!
0"
0$
0'
0(
0*
#90000000
1$
1*
#100000000
1"
0$
1(
0*
